[
  {
    "name": "Michael Jordan's game-worn sneakers",
    "url": "https://cdn.cnn.com/cnnnext/dam/assets/200814092431-01b-michael-jordan-sneakers-auction-super-169.jpg"
  },
  {
    "name": "Rockfield Men's Sneaker",
    "url": "https://images-na.ssl-images-amazon.com/images/I/611TWd7sDIL._UY500_.jpg"
  },
  {
    "name": "The best Sneaker",
    "url": "https://static1.fashionbeans.com/wp-content/uploads/2018/07/11sneakers-top-1.jpg"
  },
  {
    "name": "Nike x MSCHF Air Max 97 Jesus Shoes –  Walk On Water",
    "url": "https://www.footshop.eu/blog/wp-content/uploads/2020/01/10.jpg"
  }
]